hubspace/__init__.py
hubspace/hubspace.py
hubspace/hubspace_device.py
hubspace/hubspace_user.py
hubspace/util.py
hubspace-1.1.2.dist-info/LICENSE
hubspace-1.1.2.dist-info/METADATA
hubspace-1.1.2.dist-info/WHEEL
hubspace-1.1.2.dist-info/top_level.txt
hubspace-1.1.2.dist-info/RECORD
