Metadata-Version: 2.1
Name: hubspace
Version: 1.1.2
Author-email: Leyla Becker <git@jan-leila.com>
License: Copyright © 2022 Leyla Becker
Project-URL: Homepage, https://github.com/jan-leila/hubspace-py
Keywords: hubspace,iot
License-File: LICENSE
